{"objectID": 459046, "objectName": "Painting", "title": "Saints Bartholomew and Simon", "primaryImage": "https://images.metmuseum.org/CRDImages/rl/original/DP-28634-001.jpg", "primaryImageSmall": "https://images.metmuseum.org/CRDImages/rl/web-large/DP-28634-001.jpg", "artistRole": "Artist", "artistDisplayName": "Master of Saint Francis", "faces": {"yolo": {"count": 2, "xyxyn": [[0.3278, 0.1421, 0.4531, 0.2439], [0.5189, 0.1459, 0.6572, 0.2461]], "xyxyn_sq": [[0.2793, 0.137, 0.5017, 0.249], [0.4786, 0.1409, 0.6975, 0.2511]]}, "dino": {"count": 2, "xyxyn": [[0.3249, 0.1341, 0.4531, 0.2464], [0.5192, 0.1449, 0.6633, 0.2489]], "xyxyn_sq": [[0.2663, 0.1285, 0.5117, 0.252], [0.4777, 0.1397, 0.7048, 0.2541]]}}}